zestrag/__init__.py
zestrag/base.py
zestrag/constants.py
zestrag/exceptions.py
zestrag/llm.py
zestrag/mineru_parser.py
zestrag/modalprocessors.py
zestrag/namespace.py
zestrag/operate.py
zestrag/prompt.py
zestrag/raganything.py
zestrag/types.py
zestrag/utils.py
zestrag/utils_graph.py
zestrag/zestrag.py
zestrag/api/__init__.py
zestrag/api/auth.py
zestrag/api/config.py
zestrag/api/gunicorn_config.py
zestrag/api/lightrag_server.py
zestrag/api/run_with_gunicorn.py
zestrag/api/utils_api.py
zestrag/api/routers/__init__.py
zestrag/api/routers/document_routes.py
zestrag/api/routers/graph_routes.py
zestrag/api/routers/ollama_api.py
zestrag/api/routers/query_routes.py
zestrag/kg/__init__.py
zestrag/kg/age_impl.py
zestrag/kg/chroma_impl.py
zestrag/kg/faiss_impl.py
zestrag/kg/gremlin_impl.py
zestrag/kg/json_doc_status_impl.py
zestrag/kg/json_kv_impl.py
zestrag/kg/milvus_impl.py
zestrag/kg/mongo_impl.py
zestrag/kg/nano_vector_db_impl.py
zestrag/kg/neo4j_impl.py
zestrag/kg/networkx_impl.py
zestrag/kg/postgres_impl.py
zestrag/kg/qdrant_impl.py
zestrag/kg/redis_impl.py
zestrag/kg/shared_storage.py
zestrag/kg/tidb_impl.py
zestrag/llm/__init__.py
zestrag/llm/anthropic.py
zestrag/llm/azure_openai.py
zestrag/llm/bedrock.py
zestrag/llm/hf.py
zestrag/llm/jina.py
zestrag/llm/llama_index_impl.py
zestrag/llm/lmdeploy.py
zestrag/llm/lollms.py
zestrag/llm/nvidia_openai.py
zestrag/llm/ollama.py
zestrag/llm/openai.py
zestrag/llm/siliconcloud.py
zestrag/llm/zhipu.py
zestrag/prompt_config/__init__.py
zestrag/prompt_config/base_prompt.py
zestrag/prompt_config/chinese_prompt.py
zestrag/tools/__init__.py
zestrag/tools/zestrag_visualizer/__init__.py
zestrag/tools/zestrag_visualizer/graph_visualizer.py
zestrag-0.1.1.dist-info/licenses/LICENSE
zestrag-0.1.1.dist-info/METADATA
zestrag-0.1.1.dist-info/WHEEL
zestrag-0.1.1.dist-info/top_level.txt
zestrag-0.1.1.dist-info/RECORD
